{
    "device_image_url": "https://fdn2.gsmarena.com/vv/bigpic/tecno-camon-50-4g.jpg",
    "specifications": {
        "Network": {
            "Technology": "GSM / HSPA / LTE",
            "2G bands": "GSM 850 / 900 / 1800 / 1900 ",
            "3G bands": "HSDPA 850 / 900 / 1700(AWS) / 1900 / 2100 ",
            "4G bands": " LTE",
            "Speed": "HSPA, LTE"
        },
        "Launch": {
            "Announced": "2026, February 17",
            "Status": "Coming soon. Exp. release 2026, March"
        },
        "Body": {
            "Dimensions": "162.4 x 77.2 x 7.5 mm (6.39 x 3.04 x 0.30 in)",
            "Weight": "-",
            "SIM": "Nano-SIM + Nano-SIM",
            "\u00a0": "IP68/IP69K dust tight and water resistant (high pressure water jets; immersible up to 2m for 30 min)\r\nMIL-STD-810 compliant*\r\n* does not guarantee ruggedness or use in extreme conditions"
        },
        "Display": {
            "Type": "AMOLED, 144Hz",
            "Size": "6.78 inches, 112.1 cm2 (~89.4% screen-to-body ratio)",
            "Resolution": "1208 x 2644 pixels, 19.5:9 ratio (~429 ppi density)",
            "Protection": "Unspecified",
            "\u00a0": "HDR image support"
        },
        "Platform": {
            "OS": "Android 16, up to 3 major Android upgrades, HIOS 16",
            "Chipset": "Mediatek Helio G200 Ultimate (6 nm)",
            "CPU": "Octa-core (2x2.2 GHz Cortex-A76 & 6x2.0 GHz Cortex-A55)",
            "GPU": "Mali-G57 MC2 (1.1GHz)"
        },
        "Memory": {
            "Card slot": "Unspecified",
            "Internal": "256GB 8GB RAM"
        },
        "Main Camera": {
            "Dual": "50 MP, f/1.8, 23mm (wide), 1/1.56\", 1.0\u00b5m, PDAF, OIS\r\n8 MP, f/2.2, 14mm, 112\u02da (ultrawide), AF",
            "Features": "Dual-LED flash, HDR, panorama",
            "Video": "1080p@30fps"
        },
        "Selfie camera": {
            "Single": "32 MP, f/2.5, (wide)",
            "Video": "1080p@30fps"
        },
        "Sound": {
            "Loudspeaker ": "Yes, with stereo speakers",
            "3.5mm jack ": "No",
            "\u00a0": "24-bit/192kHz Hi-Res audio"
        },
        "Comms": {
            "WLAN": "Yes",
            "Bluetooth": "Yes",
            "Positioning": "GPS",
            "NFC": "Yes",
            "Infrared port": "Yes",
            "Radio": "FM radio",
            "USB": "USB Type-C 2.0, OTG"
        },
        "Features": {
            "Sensors": "Fingerprint (under display, optical), accelerometer, proximity, compass"
        },
        "Battery": {
            "Type": "6150 mAh",
            "Charging": "45W wired"
        },
        "Misc": {
            "Colors": "Moonlight black, Malachite green, Nebula titanium, Fir green, Lavender mist, Mint cream",
            "Models": "CN5"
        }
    }
}